{
  "PuckLocations": [
    {
      "puckLocationsRed": [
        [
          83,
          735
        ],
        [
          438,
          715
        ],
        [
          165,
          686
        ],
        [
          366,
          936
        ]
      ],
      "puckLocationsBlue": [
        [
          314,
          1113
        ],
        [
          507,
          991
        ],
        [
          118,
          928
        ],
        [
          250,
          985
        ]
      ],
      "id": 1
    }
  ],
  "TableData": [
    {
      "PythonShotCounter": 25,
      "GameType": "spaceInvaders",
      "ShotsPlayed": 0,
      "RoundsPlayed": 5,
      "GameState": "inProgress",
      "RoundScoresRed": [
        1,
        1,
        13,
        13,
        13
      ],
      "RoundScoresBlue": [
        0,
        1,
        11,
        11,
        1
      ],
      "id": 1
    }
  ]
}